xorange/sphinx/theme/VERSION
xorange/sphinx/theme/__init__.py
xorange/sphinx/theme/breadcrumbs.html
xorange/sphinx/theme/footer.html
xorange/sphinx/theme/layout.html
xorange/sphinx/theme/theme.conf
xorange/sphinx/theme/static/favicon.ico
xorange/sphinx/theme/static/nextstrain-logo.svg
xorange/sphinx/theme/static/css/xorange.css
xorange/sphinx/theme/static/js/theme.js
xorange/sphinx/theme/static/logos/bz_logo.png
xorange/sphinx/theme/static/logos/fred-hutch-logo-small.png
xorange/sphinx/theme/static/logos/fred-hutch-logo.png
xorange/sphinx/theme/static/logos/icon.png
xorange/sphinx/theme/static/logos/mapbox-logo-black.svg
xorange/sphinx/theme/static/logos/nextstrain-logo-small.png
xorange/sphinx/theme/static/logos/nextstrain_should_be_svg.png
xorange/sphinx/theme/static/logos/nih-logo-small.png
xorange/sphinx/theme/static/logos/nih-logo.jpg
xorange/sphinx/theme/static/logos/osp-logo-small.png
xorange/sphinx/theme/static/logos/sib-logo.png
xorange/sphinx/theme/static/logos/unibas-logo.svg
xorange/sphinx/theme/static/team/allison-black.jpg
xorange/sphinx/theme/static/team/barney-potter.jpg
xorange/sphinx/theme/static/team/cassia-wagner.jpg
xorange/sphinx/theme/static/team/charlton-callender.jpg
xorange/sphinx/theme/static/team/colin-megill.jpg
xorange/sphinx/theme/static/team/eli-harkins.jpg
xorange/sphinx/theme/static/team/emma-hodcroft.jpg
xorange/sphinx/theme/static/team/ivan-aksamentov.jpg
xorange/sphinx/theme/static/team/james-hadfield.jpg
xorange/sphinx/theme/static/team/john-huddleston.jpg
xorange/sphinx/theme/static/team/jover-lee.jpg
xorange/sphinx/theme/static/team/kairsten-fay.jpg
xorange/sphinx/theme/static/team/louise-moncla.jpg
xorange/sphinx/theme/static/team/miguel-parades.jpg
xorange/sphinx/theme/static/team/misja-ilcisin.jpg
xorange/sphinx/theme/static/team/moira-zuber.jpg
xorange/sphinx/theme/static/team/pavel-sagulenko.jpg
xorange/sphinx/theme/static/team/richard-neher.jpg
xorange/sphinx/theme/static/team/sidney-bell.jpg
xorange_sphinx_theme-2022.12.dist-info/LICENSE
xorange_sphinx_theme-2022.12.dist-info/METADATA
xorange_sphinx_theme-2022.12.dist-info/WHEEL
xorange_sphinx_theme-2022.12.dist-info/entry_points.txt
xorange_sphinx_theme-2022.12.dist-info/top_level.txt
xorange_sphinx_theme-2022.12.dist-info/RECORD
